{"user":{"id":23,"username":"testadmin","email":"testadmin@skynote.com","displayName":"Test Administrator","bio":null,"avatar":null,"currentlyReading":null,"favoriteQuote":null,"isAdmin":true,"points":0,"followersCount":0,"followingCount":0,"emailVerified":true,"emailVerificationToken":null,"notificationPreferences":{"reposts":false,"comments":true,"likesOnPosts":true,"newFollowers":true,"pushNotifications":true,"emailNotifications":true},"createdAt":"2025-06-30T02:59:34.336Z"},"token":"eyJhbGciOiJIUzI1NiIsInR5cCI6IkpXVCJ9.eyJpZCI6MjMsInVzZXJuYW1lIjoidGVzdGFkbWluIiwiaXNBZG1pbiI6dHJ1ZSwiaWF0IjoxNzUxMjUyNTA3fQ.9TAjacV8tzBH3Y5Bz_QVbvrBSTr3xz4pH-fzg882rto"}